[
	{
		"num" : "0",
		"date" : "2018/08/15 22:05:30 1",
		"address" : "广东省珠海市",
		"content" : "我记得网络上有这样一段话：“20岁的贪玩，造就了30岁的无奈。30岁的无奈，导致了40岁的无为！40岁的无为，奠定了50岁的失败。酿造了一辈子的碌碌无为！”成功的人生等不得，请不要在该奋斗的年纪选择了安逸，否则，当父母需要你时，除了泪水，你一无所有；当孩子需要你时，除了惭愧，你一无所有；当自己回首过去，除了蹉跎，你还是一无所有！",
		"image" : ["https://raw.githubusercontent.com/GGTechnology/AppleNote/master/Source/image/applenote1.PNG"]
	},
	{
		"num" : "1",
		"date" : "2019/10/01 06:00:01 7",
		"address" : "广东省深圳市",
		"content" : "我从来不以为学历有什么重要，天才都不是科班，但，不是科班，连龙套都跑不了。　　你必须把那些浮如飘絮的思绪，渐渐转化为清晰的思路和简单的文字。华丽和漂浮都不易长久。你要知道，给予文字阅读快感不够的，内容，思想，境界，灵魂，精神和智慧，这些才重要。不要多看那些和你一个路数的女作家的文字。不要琐碎，无病呻吟。不要想到什么就写。不要流连于小感伤和小感动。我要你相信温暖，美好，信任，尊严，坚强这些老掉牙的字眼。　　我不要你颓废，空虚，迷茫，糟践自己，伤害别人。我不要你把自己处理得一团糟。节制自己的感情并且珍惜它，明白这种感情不是任何人都能要。",
		"image" : ["https://raw.githubusercontent.com/GGTechnology/AppleNote/master/Source/image/applenote2.PNG"]
	}
]